{
  "raw_text": "NOT A MEMBER YET? DOWNLOAD & JOIN NOW!\nTENT\nAPP\nGET EXCLUSIVE OFFERS\nAND EARN REWARDS\nENJOY ONL INE GROCERY\nDELIVERY\nT&T Supermarket\nOsaka Store\n#1000-3700 No.3 Rd. Richmond,B.C. V6X 3X2\nPh: (604) 276-8808 / Gst# 135747137RT\n01/22/26 6:25:01 PM\nLulu\n***031381354\n$0.00\nGROCERY\nHEINZ TOMATO KETCHUP 375ML\nU $4.49\n1\nT&T SLICED RUOQIANG RED DATES\nW $3.99\nGTER\n(SALE) WJ SHREDDED PSVD VEGETABLE\nW $2.27\n(11)\nFOOD\nHOUSE NOODLE FLAT (RAW)\nW $3.99\nHEAT\nSAKURA PRMIUM PORK BELLY SLICE\n2 @ $8.99ea.\nW $17.98\nPRODUCE\nPOTATO\n0.500 kg @ $2.14/kg\nW $1.07\n(SALE) GREEN BEANS\n0.520 kg @ $4.37/kg\nW $2.27\n(11)\nDELI\nDAIRYLAND 3.25% LACTOSE FREE\nW $6.69\nDL 3.25% EL\nBottle deposit\n$0.10\nEnv fee (CRF)\n$0.01\nGOLD PLUM SALTED DUCK EGGS\nW $5.99\nSYNEAR FRIED STICKS\nW $5.25\nPoints 40\n$0.00\n$54.10\nTOTAL New Gift card (-) [******0393]\n$54.10\nGift balance: 145.90\nPoints in this transaction: 40\nPoints balance\n1260\nItem count: 11\nTrans: 907212\nTerminal:050108015-005005\nSTORE: 10005\nCODE: 012226 182505 7212 10005\nFULL DETAILS OF T&T SUPERMARKET'S REFUND POLICY ARE\nAVAILABLE AT IN-STORE.\nT&T a\nMonthly chances to win $1,000 PC Gift Card or 1 Million\nTELL US HOW WE DID TODAY\na\nto your friends?\n1-800-531-2928 for\nfull\nEligible amount for point calculation: $53.99",
  "entities": {
    "total_amount": {
      "value": "$53.99",
      "confidence": 0.6387807846069335
    },
    "supplier_name": {
      "value": "T&T Supermarket",
      "confidence": 0.7150450897216797
    }
  },
  "line_items": [
    {
      "raw_text": "***031381354",
      "product_name": "***031381354",
      "quantity": null,
      "unit": null,
      "unit_price": 0.0,
      "line_total": null,
      "is_on_sale": false,
      "category": null
    },
    {
      "raw_text": "HEINZ TOMATO KETCHUP 375ML",
      "product_name": "HEINZ TOMATO KETCHUP 375ML",
      "quantity": null,
      "unit": null,
      "unit_price": null,
      "line_total": null,
      "is_on_sale": false,
      "category": null
    },
    {
      "raw_text": "18T SLICED RUDQIANG RED DATES",
      "product_name": "18T SLICED RUDQIANG RED DATES",
      "quantity": null,
      "unit": null,
      "unit_price": null,
      "line_total": null,
      "is_on_sale": false,
      "category": null
    },
    {
      "raw_text": "(SALE) WJ SHREDDED PSVD VEGETABLE",
      "product_name": "(SALE) WJ SHREDDED PSVD VEGETABLE",
      "quantity": null,
      "unit": null,
      "unit_price": null,
      "line_total": null,
      "is_on_sale": false,
      "category": null
    },
    {
      "raw_text": "SAKURA PRMIUM PORK BELLY SLICE",
      "product_name": "SAKURA PRMIUM PORK BELLY SLICE",
      "quantity": 2.0,
      "unit": null,
      "unit_price": null,
      "line_total": null,
      "is_on_sale": false,
      "category": null
    },
    {
      "raw_text": "POTATO",
      "product_name": "POTATO",
      "quantity": null,
      "unit": null,
      "unit_price": null,
      "line_total": null,
      "is_on_sale": false,
      "category": null
    },
    {
      "raw_text": "(SALE) GREEN BEANS",
      "product_name": "(SALE) GREEN BEANS",
      "quantity": null,
      "unit": null,
      "unit_price": null,
      "line_total": null,
      "is_on_sale": false,
      "category": null
    },
    {
      "raw_text": "DAIRYLAND 3.25% LACTOSE FREE",
      "product_name": "DAIRYLAND 3.25% LACTOSE FREE",
      "quantity": null,
      "unit": null,
      "unit_price": null,
      "line_total": null,
      "is_on_sale": false,
      "category": null
    },
    {
      "raw_text": "Bottle deposit",
      "product_name": "Bottle deposit",
      "quantity": null,
      "unit": null,
      "unit_price": 0.1,
      "line_total": null,
      "is_on_sale": false,
      "category": null
    },
    {
      "raw_text": "Env fee (CRF)",
      "product_name": "Env fee (CRF)",
      "quantity": null,
      "unit": null,
      "unit_price": 0.01,
      "line_total": null,
      "is_on_sale": false,
      "category": null
    },
    {
      "raw_text": "GOLD PLUM SALTED DUCK EGGS",
      "product_name": "GOLD PLUM SALTED DUCK EGGS",
      "quantity": null,
      "unit": null,
      "unit_price": null,
      "line_total": null,
      "is_on_sale": false,
      "category": null
    },
    {
      "raw_text": "SYNEAR FRIED STICKS",
      "product_name": "SYNEAR FRIED STICKS",
      "quantity": null,
      "unit": null,
      "unit_price": null,
      "line_total": null,
      "is_on_sale": false,
      "category": null
    }
  ],
  "merchant_name": "T&T Supermarket",
  "metadata": {
    "ocr_provider": "aws_textract"
  },
  "total": 53.99
}